fuzzfetch/__init__.py
fuzzfetch/__main__.py
fuzzfetch/args.py
fuzzfetch/core.py
fuzzfetch/download.py
fuzzfetch/errors.py
fuzzfetch/extract.py
fuzzfetch/models.py
fuzzfetch/path.py
fuzzfetch/py.typed
fuzzfetch/utils.py
fuzzfetch-16.1.0.dist-info/licenses/LICENSE.md
fuzzfetch-16.1.0.dist-info/METADATA
fuzzfetch-16.1.0.dist-info/WHEEL
fuzzfetch-16.1.0.dist-info/entry_points.txt
fuzzfetch-16.1.0.dist-info/top_level.txt
fuzzfetch-16.1.0.dist-info/RECORD
