Metadata-Version: 2.4
Name: fuzzfetch
Version: 16.1.0
Summary: Downloader for firefox/jsshell builds.
Home-page: https://github.com/MozillaSecurity/fuzzfetch
Maintainer: Mozilla Fuzzing Team
Maintainer-email: fuzzing@mozilla.com
License: MPL 2.0
Keywords: fuzz fuzzing security test testing
Platform: any
Classifier: Development Status :: 5 - Production/Stable
Classifier: Intended Audience :: Developers
Classifier: License :: OSI Approved :: Mozilla Public License 2.0 (MPL 2.0)
Classifier: Programming Language :: Python :: 3
Classifier: Topic :: Security
Classifier: Topic :: Software Development :: Testing
Requires-Python: >=3.10
License-File: LICENSE.md
Requires-Dist: pytz
Requires-Dist: requests
Dynamic: license-file
